hightop/__init__.py
hightop-0.2.0.dist-info/LICENSE.txt
hightop-0.2.0.dist-info/METADATA
hightop-0.2.0.dist-info/WHEEL
hightop-0.2.0.dist-info/top_level.txt
hightop-0.2.0.dist-info/RECORD
