Metadata-Version: 2.1
Name: hightop
Version: 0.2.0
Summary: A nice shortcut for group count queries with Django
Home-page: https://github.com/ankane/hightop.py
Author: Andrew Kane
Author-email: andrew@ankane.org
License: MIT
Requires-Python: >=3.8
License-File: LICENSE.txt
Requires-Dist: Django
